ditto_pandas/__init__.py
ditto_pandas/_version.py
ditto_pandas/io.py
ditto_pandas/marks.py
pytest_ditto_pandas-0.0.1.dist-info/METADATA
pytest_ditto_pandas-0.0.1.dist-info/WHEEL
pytest_ditto_pandas-0.0.1.dist-info/entry_points.txt
pytest_ditto_pandas-0.0.1.dist-info/licenses/LICENSE
pytest_ditto_pandas-0.0.1.dist-info/RECORD
